django_settings_local/__init__.py
django_settings_local/__main__.py
django_settings_local/cute_python.py
django_settings_local/dsl.py
django_settings_local/settings_local.py
django_settings_local-0.2.1.dist-info/LICENSE
django_settings_local-0.2.1.dist-info/METADATA
django_settings_local-0.2.1.dist-info/WHEEL
django_settings_local-0.2.1.dist-info/entry_points.txt
django_settings_local-0.2.1.dist-info/top_level.txt
django_settings_local-0.2.1.dist-info/RECORD
