Metadata-Version: 2.1
Name: django-settings-local
Version: 0.2.1
Summary: Manage Django Local Settings
Home-page: https://github.com/fasih/django-settings-local
Author: Fasih Ahmad Fakhri
Author-email: fasih@email.com
License: GPL-3.0
Keywords: django,local,settings
Platform: UNKNOWN
Classifier: Development Status :: 5 - Production/Stable
Classifier: Framework :: Django
Classifier: Intended Audience :: Developers
Classifier: License :: OSI Approved :: GNU General Public License v3 (GPLv3)
Classifier: Programming Language :: Python :: 3
Classifier: Topic :: Software Development :: Libraries
Requires-Python: >=3.6
